ekispertapi_sdk_comm/__init__.py
ekispertapi_sdk_comm/client.py
ekispertapi_sdk_comm/utils.py
ekispertapi_sdk_comm/__pycache__/__init__.cpython-311.pyc
ekispertapi_sdk_comm/__pycache__/__init__.cpython-312.pyc
ekispertapi_sdk_comm/__pycache__/__init__.cpython-313.pyc
ekispertapi_sdk_comm/__pycache__/base.cpython-312.pyc
ekispertapi_sdk_comm/__pycache__/base.cpython-313.pyc
ekispertapi_sdk_comm/__pycache__/client.cpython-311.pyc
ekispertapi_sdk_comm/__pycache__/client.cpython-312.pyc
ekispertapi_sdk_comm/__pycache__/client.cpython-313.pyc
ekispertapi_sdk_comm/__pycache__/model.cpython-312.pyc
ekispertapi_sdk_comm/__pycache__/query.cpython-312.pyc
ekispertapi_sdk_comm/__pycache__/utils.cpython-311.pyc
ekispertapi_sdk_comm/models/__init__.py
ekispertapi_sdk_comm/models/assign_status.py
ekispertapi_sdk_comm/models/base.py
ekispertapi_sdk_comm/models/car.py
ekispertapi_sdk_comm/models/change.py
ekispertapi_sdk_comm/models/cost.py
ekispertapi_sdk_comm/models/cource.py
ekispertapi_sdk_comm/models/formation.py
ekispertapi_sdk_comm/models/geo_point.py
ekispertapi_sdk_comm/models/line.py
ekispertapi_sdk_comm/models/operational_state.py
ekispertapi_sdk_comm/models/pass_status.py
ekispertapi_sdk_comm/models/point.py
ekispertapi_sdk_comm/models/prefecture.py
ekispertapi_sdk_comm/models/price.py
ekispertapi_sdk_comm/models/relation.py
ekispertapi_sdk_comm/models/repayment_list.py
ekispertapi_sdk_comm/models/repayment_ticket.py
ekispertapi_sdk_comm/models/route.py
ekispertapi_sdk_comm/models/section_separator.py
ekispertapi_sdk_comm/models/station.py
ekispertapi_sdk_comm/models/stop.py
ekispertapi_sdk_comm/models/teiki.py
ekispertapi_sdk_comm/models/teiki_route.py
ekispertapi_sdk_comm/models/teiki_route_section.py
ekispertapi_sdk_comm/models/trip_option.py
ekispertapi_sdk_comm/models/__pycache__/assign_status.cpython-311.pyc
ekispertapi_sdk_comm/models/__pycache__/base.cpython-311.pyc
ekispertapi_sdk_comm/models/__pycache__/car.cpython-311.pyc
ekispertapi_sdk_comm-0.6.0.dist-info/licenses/LICENSE
ekispertapi_sdk_comm-0.6.0.dist-info/METADATA
ekispertapi_sdk_comm-0.6.0.dist-info/WHEEL
ekispertapi_sdk_comm-0.6.0.dist-info/top_level.txt
ekispertapi_sdk_comm-0.6.0.dist-info/RECORD
